chinese_administrative_divisions/__init__.py
chinese_administrative_divisions/data.py
chinese_administrative_divisions/query.py
chinese_administrative_divisions-1.0.dist-info/METADATA
chinese_administrative_divisions-1.0.dist-info/WHEEL
chinese_administrative_divisions-1.0.dist-info/top_level.txt
chinese_administrative_divisions-1.0.dist-info/RECORD
