Metadata-Version: 2.1
Name: chinese-administrative-divisions
Version: 1.0
Summary: 中国行政区划查询包
Home-page: https://github.com/zgxdxf/good-fortune.git
Author: wangxueming
Author-email: zgxdxf@hotmail.com
License: UNKNOWN
Platform: UNKNOWN
Classifier: Programming Language :: Python :: 3
Classifier: License :: OSI Approved :: MIT License
Classifier: Operating System :: OS Independent
Requires-Python: >=3.6
